dud/__init__.py
dud/main.py
dud-0.1.0.dist-info/entry_points.txt
dud-0.1.0.dist-info/LICENSE
dud-0.1.0.dist-info/WHEEL
dud-0.1.0.dist-info/METADATA
dud-0.1.0.dist-info/RECORD
