Metadata-Version: 2.1
Name: dud
Version: 0.1.0
Summary: experimental static site generator in python
License: MIT
Author: Amal Shaji
Author-email: 18011385+amalshaji@users.noreply.github.com
Requires-Python: >=3.8,<4.0
Classifier: License :: OSI Approved :: MIT License
Classifier: Programming Language :: Python :: 3
Classifier: Programming Language :: Python :: 3.10
Classifier: Programming Language :: Python :: 3.8
Classifier: Programming Language :: Python :: 3.9
Requires-Dist: Flask (>=2.0.2,<3.0.0)
Requires-Dist: typer (>=0.4.0,<0.5.0)
